{"rollout/ep_rew_mean": -13344724.648878, "rollout/ep_len_mean": 672.6666666666666, "time/fps": 3491, "time/time_elapsed": 2, "time/total_timesteps": 10000}
{"rollout/ep_rew_mean": -15946761.292391201, "rollout/ep_len_mean": 803.6, "time/fps": 3678, "time/time_elapsed": 5, "time/total_timesteps": 20000}
{"rollout/ep_rew_mean": -15519779.314706888, "rollout/ep_len_mean": 781.2222222222222, "time/fps": 3750, "time/time_elapsed": 7, "time/total_timesteps": 30000}
{"rollout/ep_rew_mean": -16299834.835858816, "rollout/ep_len_mean": 821.0, "time/fps": 3811, "time/time_elapsed": 10, "time/total_timesteps": 40000}
{"train/iterations": 0, "train/delta_std": 0.05, "train/learning_rate": 0.0018, "train/step_size": 2.5518212543040875e-11, "rollout/return_std": 8817232.0, "time/fps": 3775, "time/time_elapsed": 13, "time/total_timesteps": 50000}
{"rollout/ep_rew_mean": -20020470.0, "rollout/ep_len_mean": 1000.0, "time/fps": 3796, "time/time_elapsed": 15, "time/total_timesteps": 60000}
{"rollout/ep_rew_mean": -19905350.4072242, "rollout/ep_len_mean": 1000.0, "time/fps": 3812, "time/time_elapsed": 18, "time/total_timesteps": 70000}
{"rollout/ep_rew_mean": -19901556.711183716, "rollout/ep_len_mean": 1000.0, "time/fps": 3825, "time/time_elapsed": 20, "time/total_timesteps": 80000}
{"rollout/ep_rew_mean": -18086205.91448618, "rollout/ep_len_mean": 909.8181818181819, "time/fps": 3835, "time/time_elapsed": 23, "time/total_timesteps": 90000}
{"rollout/ep_rew_mean": -18370658.083340306, "rollout/ep_len_mean": 923.6923076923077, "time/fps": 3854, "time/time_elapsed": 25, "time/total_timesteps": 100000}
{"train/iterations": 1, "train/delta_std": 0.05, "train/learning_rate": 0.0018, "train/step_size": 3.327710676459539e-11, "rollout/return_std": 6761405.5, "rollout/ep_rew_mean": -19814173.167756, "rollout/ep_len_mean": 1000.0, "time/fps": 3858, "time/time_elapsed": 28, "time/total_timesteps": 110000}
{"rollout/ep_rew_mean": -14928046.473087998, "rollout/ep_len_mean": 752.25, "time/fps": 3862, "time/time_elapsed": 31, "time/total_timesteps": 120000}
{"rollout/ep_rew_mean": -14977642.267356373, "rollout/ep_len_mean": 752.5, "time/fps": 3866, "time/time_elapsed": 33, "time/total_timesteps": 130000}
{"rollout/ep_rew_mean": -15968445.054185297, "rollout/ep_len_mean": 802.0, "time/fps": 3869, "time/time_elapsed": 36, "time/total_timesteps": 140000}
{"rollout/ep_rew_mean": -16894824.176363304, "rollout/ep_len_mean": 847.6923076923077, "time/fps": 3865, "time/time_elapsed": 38, "time/total_timesteps": 150000}
{"train/iterations": 2, "train/delta_std": 0.05, "train/learning_rate": 0.0018, "train/step_size": 2.811369366473304e-11, "rollout/return_std": 8003217.5, "time/fps": 3868, "time/time_elapsed": 41, "time/total_timesteps": 160000}
{"rollout/ep_rew_mean": -19813973.401800003, "rollout/ep_len_mean": 1000.0, "time/fps": 3870, "time/time_elapsed": 43, "time/total_timesteps": 170000}
{"rollout/ep_rew_mean": -19869014.0759094, "rollout/ep_len_mean": 1000.0, "time/fps": 3871, "time/time_elapsed": 46, "time/total_timesteps": 180000}
{"rollout/ep_rew_mean": -19857788.661555875, "rollout/ep_len_mean": 1000.0, "time/fps": 3872, "time/time_elapsed": 49, "time/total_timesteps": 190000}
{"rollout/ep_rew_mean": -19856715.6384539, "rollout/ep_len_mean": 1000.0, "time/fps": 3873, "time/time_elapsed": 51, "time/total_timesteps": 200000}
{"rollout/ep_rew_mean": -19876188.862523463, "rollout/ep_len_mean": 1000.0, "time/fps": 3875, "time/time_elapsed": 54, "time/total_timesteps": 210000}
{"rollout/ep_rew_mean": -19884329.61031127, "rollout/ep_len_mean": 1000.0, "time/fps": 3876, "time/time_elapsed": 56, "time/total_timesteps": 220000}
{"train/iterations": 3, "train/delta_std": 0.05, "train/learning_rate": 0.0018, "train/step_size": 2.0922656940314255e-09, "rollout/return_std": 107538.921875, "rollout/ep_rew_mean": -19959288.3921825, "rollout/ep_len_mean": 1000.0, "time/fps": 3878, "time/time_elapsed": 59, "time/total_timesteps": 230000}
{"rollout/ep_rew_mean": -19932196.99172175, "rollout/ep_len_mean": 1000.0, "time/fps": 3879, "time/time_elapsed": 61, "time/total_timesteps": 240000}
{"rollout/ep_rew_mean": -19788081.333484285, "rollout/ep_len_mean": 1000.0, "time/fps": 3880, "time/time_elapsed": 64, "time/total_timesteps": 250000}
{"rollout/ep_rew_mean": -19821606.759011667, "rollout/ep_len_mean": 1000.0, "time/fps": 3882, "time/time_elapsed": 66, "time/total_timesteps": 260000}
{"rollout/ep_rew_mean": -19819609.212961417, "rollout/ep_len_mean": 1000.0, "time/fps": 3884, "time/time_elapsed": 69, "time/total_timesteps": 270000}
{"rollout/ep_rew_mean": -18491216.448821533, "rollout/ep_len_mean": 934.2666666666667, "time/fps": 3886, "time/time_elapsed": 72, "time/total_timesteps": 280000}
{"train/iterations": 4, "train/delta_std": 0.05, "train/learning_rate": 0.0018, "train/step_size": 4.558838723189851e-11, "rollout/return_std": 4935467.5, "rollout/ep_rew_mean": -19945838.219085, "rollout/ep_len_mean": 1000.0, "time/fps": 3887, "time/time_elapsed": 74, "time/total_timesteps": 290000}
{"rollout/ep_rew_mean": -19901585.43532725, "rollout/ep_len_mean": 1000.0, "time/fps": 3887, "time/time_elapsed": 77, "time/total_timesteps": 300000}
{"rollout/ep_rew_mean": -19879971.724398427, "rollout/ep_len_mean": 1000.0, "time/fps": 3888, "time/time_elapsed": 79, "time/total_timesteps": 310000}
{"rollout/ep_rew_mean": -19855848.364863776, "rollout/ep_len_mean": 1000.0, "time/fps": 3892, "time/time_elapsed": 82, "time/total_timesteps": 320000}
{"rollout/ep_rew_mean": -18357422.511644997, "rollout/ep_len_mean": 928.7692307692307, "time/fps": 3892, "time/time_elapsed": 84, "time/total_timesteps": 330000}
{"rollout/ep_rew_mean": -18565752.528921198, "rollout/ep_len_mean": 938.2666666666667, "time/fps": 3893, "time/time_elapsed": 87, "time/total_timesteps": 340000}
{"train/iterations": 5, "train/delta_std": 0.05, "train/learning_rate": 0.0018, "train/step_size": 4.649777785026288e-11, "rollout/return_std": 4838941.0, "rollout/ep_rew_mean": -19722481.649485998, "rollout/ep_len_mean": 1000.0, "time/fps": 3893, "time/time_elapsed": 89, "time/total_timesteps": 350000}
{"rollout/ep_rew_mean": -19688988.39105325, "rollout/ep_len_mean": 1000.0, "time/fps": 3894, "time/time_elapsed": 92, "time/total_timesteps": 360000}
{"rollout/ep_rew_mean": -19293329.080601852, "rollout/ep_len_mean": 1000.0, "time/fps": 3895, "time/time_elapsed": 94, "time/total_timesteps": 370000}
{"rollout/ep_rew_mean": -19438011.483315334, "rollout/ep_len_mean": 1000.0, "time/fps": 3895, "time/time_elapsed": 97, "time/total_timesteps": 380000}
{"rollout/ep_rew_mean": -19471467.63583425, "rollout/ep_len_mean": 1000.0, "time/fps": 3897, "time/time_elapsed": 100, "time/total_timesteps": 390000}
{"rollout/ep_rew_mean": -19523598.107225213, "rollout/ep_len_mean": 1000.0, "time/fps": 3897, "time/time_elapsed": 102, "time/total_timesteps": 400000}
{"train/iterations": 6, "train/delta_std": 0.05, "train/learning_rate": 0.0018, "train/step_size": 4.5892668137925696e-11, "rollout/return_std": 4902744.0, "rollout/ep_rew_mean": -19863123.420718, "rollout/ep_len_mean": 1000.0, "time/fps": 3898, "time/time_elapsed": 105, "time/total_timesteps": 410000}
{"rollout/ep_rew_mean": -15972776.39244, "rollout/ep_len_mean": 803.6, "time/fps": 3898, "time/time_elapsed": 107, "time/total_timesteps": 420000}
{"rollout/ep_rew_mean": -17464557.379635375, "rollout/ep_len_mean": 877.25, "time/fps": 3899, "time/time_elapsed": 110, "time/total_timesteps": 430000}
{"rollout/ep_rew_mean": -17913620.9699935, "rollout/ep_len_mean": 901.8, "time/fps": 3899, "time/time_elapsed": 112, "time/total_timesteps": 440000}
{"rollout/ep_rew_mean": -15923841.837650599, "rollout/ep_len_mean": 802.4666666666667, "time/fps": 3899, "time/time_elapsed": 115, "time/total_timesteps": 450000}
{"train/iterations": 7, "train/delta_std": 0.05, "train/learning_rate": 0.0018, "train/step_size": 2.825358176583581e-11, "rollout/return_std": 7963592.5, "rollout/ep_rew_mean": -19919750.0, "rollout/ep_len_mean": 1000.0, "time/fps": 3899, "time/time_elapsed": 117, "time/total_timesteps": 460000}
{"rollout/ep_rew_mean": -19871507.3941985, "rollout/ep_len_mean": 1000.0, "time/fps": 3900, "time/time_elapsed": 120, "time/total_timesteps": 470000}
{"rollout/ep_rew_mean": -19890231.081761, "rollout/ep_len_mean": 1000.0, "time/fps": 3900, "time/time_elapsed": 123, "time/total_timesteps": 480000}
{"rollout/ep_rew_mean": -19884109.505395446, "rollout/ep_len_mean": 1000.0, "time/fps": 3900, "time/time_elapsed": 125, "time/total_timesteps": 490000}
{"rollout/ep_rew_mean": -19890404.680578183, "rollout/ep_len_mean": 1000.0, "time/fps": 3901, "time/time_elapsed": 128, "time/total_timesteps": 500000}
{"rollout/ep_rew_mean": -18557078.435553197, "rollout/ep_len_mean": 934.8, "time/fps": 3903, "time/time_elapsed": 130, "time/total_timesteps": 510000}
{"train/iterations": 8, "train/delta_std": 0.05, "train/learning_rate": 0.0018, "train/step_size": 4.577736800737142e-11, "rollout/return_std": 4915092.5, "rollout/ep_rew_mean": -19994816.00433, "rollout/ep_len_mean": 1000.0, "time/fps": 3903, "time/time_elapsed": 133, "time/total_timesteps": 520000}
{"rollout/ep_rew_mean": -19969319.65809325, "rollout/ep_len_mean": 1000.0, "time/fps": 3904, "time/time_elapsed": 135, "time/total_timesteps": 530000}
{"rollout/ep_rew_mean": -19935062.11805017, "rollout/ep_len_mean": 1000.0, "time/fps": 3904, "time/time_elapsed": 138, "time/total_timesteps": 540000}
{"rollout/ep_rew_mean": -19911487.237173777, "rollout/ep_len_mean": 1000.0, "time/fps": 3904, "time/time_elapsed": 140, "time/total_timesteps": 550000}
{"rollout/ep_rew_mean": -19909704.38431418, "rollout/ep_len_mean": 1000.0, "time/fps": 3904, "time/time_elapsed": 143, "time/total_timesteps": 560000}
{"rollout/ep_rew_mean": -19899559.197184857, "rollout/ep_len_mean": 1000.0, "time/fps": 3905, "time/time_elapsed": 145, "time/total_timesteps": 570000}
{"train/iterations": 9, "train/delta_std": 0.05, "train/learning_rate": 0.0018, "train/step_size": 2.5566095906981445e-09, "rollout/return_std": 88007.1796875, "time/fps": 3905, "time/time_elapsed": 148, "time/total_timesteps": 580000}
{"rollout/ep_rew_mean": -19897196.208486333, "rollout/ep_len_mean": 1000.0, "time/fps": 3906, "time/time_elapsed": 151, "time/total_timesteps": 590000}
{"rollout/ep_rew_mean": -19918972.986823402, "rollout/ep_len_mean": 1000.0, "time/fps": 3906, "time/time_elapsed": 153, "time/total_timesteps": 600000}
{"rollout/ep_rew_mean": -19923054.5305555, "rollout/ep_len_mean": 1000.0, "time/fps": 3907, "time/time_elapsed": 156, "time/total_timesteps": 610000}
{"rollout/ep_rew_mean": -16629508.495876169, "rollout/ep_len_mean": 834.75, "time/fps": 3906, "time/time_elapsed": 158, "time/total_timesteps": 620000}
{"rollout/ep_rew_mean": -17295844.859646734, "rollout/ep_len_mean": 867.8, "time/fps": 3906, "time/time_elapsed": 161, "time/total_timesteps": 630000}
{"train/iterations": 10, "train/delta_std": 0.05, "train/learning_rate": 0.0018, "train/step_size": 3.3198679916246476e-11, "rollout/return_std": 6777378.0, "rollout/ep_rew_mean": -19986446.807831, "rollout/ep_len_mean": 1000.0, "time/fps": 3907, "time/time_elapsed": 163, "time/total_timesteps": 640000}
{"rollout/ep_rew_mean": -19918792.883906253, "rollout/ep_len_mean": 1000.0, "time/fps": 3907, "time/time_elapsed": 166, "time/total_timesteps": 650000}
{"rollout/ep_rew_mean": -19858870.2454065, "rollout/ep_len_mean": 1000.0, "time/fps": 3907, "time/time_elapsed": 168, "time/total_timesteps": 660000}
{"rollout/ep_rew_mean": -17876669.5457621, "rollout/ep_len_mean": 902.3, "time/fps": 3908, "time/time_elapsed": 171, "time/total_timesteps": 670000}
{"rollout/ep_rew_mean": -18220788.370868083, "rollout/ep_len_mean": 918.5833333333334, "time/fps": 3908, "time/time_elapsed": 173, "time/total_timesteps": 680000}
{"rollout/ep_rew_mean": -18525390.270736203, "rollout/ep_len_mean": 934.8666666666667, "time/fps": 3908, "time/time_elapsed": 176, "time/total_timesteps": 690000}
{"train/iterations": 11, "train/delta_std": 0.05, "train/learning_rate": 0.0018, "train/step_size": 4.574733300510836e-11, "rollout/return_std": 4918319.5, "rollout/ep_rew_mean": -19760652.456231, "rollout/ep_len_mean": 1000.0, "time/fps": 3908, "time/time_elapsed": 179, "time/total_timesteps": 700000}
{"rollout/ep_rew_mean": -13221197.616415, "rollout/ep_len_mean": 672.3333333333334, "time/fps": 3909, "time/time_elapsed": 181, "time/total_timesteps": 710000}
{"rollout/ep_rew_mean": -14909737.152519625, "rollout/ep_len_mean": 754.25, "time/fps": 3909, "time/time_elapsed": 184, "time/total_timesteps": 720000}
{"rollout/ep_rew_mean": -16203656.110932093, "rollout/ep_len_mean": 821.2727272727273, "time/fps": 3912, "time/time_elapsed": 186, "time/total_timesteps": 730000}
{"rollout/ep_rew_mean": -15573492.589041501, "rollout/ep_len_mean": 788.5714285714286, "time/fps": 3912, "time/time_elapsed": 189, "time/total_timesteps": 740000}
{"train/iterations": 12, "train/delta_std": 0.05, "train/learning_rate": 0.0018, "train/step_size": 2.837915492881482e-11, "rollout/return_std": 7928354.5, "rollout/ep_rew_mean": -20005934.666284, "rollout/ep_len_mean": 1000.0, "time/fps": 3912, "time/time_elapsed": 191, "time/total_timesteps": 750000}
{"rollout/ep_rew_mean": -15022347.7064185, "rollout/ep_len_mean": 754.25, "time/fps": 3913, "time/time_elapsed": 194, "time/total_timesteps": 760000}
{"rollout/ep_rew_mean": -16896722.94069157, "rollout/ep_len_mean": 859.5714285714286, "time/fps": 3914, "time/time_elapsed": 196, "time/total_timesteps": 770000}
{"rollout/ep_rew_mean": -17564951.199621, "rollout/ep_len_mean": 890.7777777777778, "time/fps": 3914, "time/time_elapsed": 199, "time/total_timesteps": 780000}
{"rollout/ep_rew_mean": -18144494.051401917, "rollout/ep_len_mean": 918.0833333333334, "time/fps": 3914, "time/time_elapsed": 201, "time/total_timesteps": 790000}
{"rollout/ep_rew_mean": -18380719.964429926, "rollout/ep_len_mean": 929.7857142857143, "time/fps": 3914, "time/time_elapsed": 204, "time/total_timesteps": 800000}
{"train/iterations": 13, "train/delta_std": 0.05, "train/learning_rate": 0.0018, "train/step_size": 4.574857506711716e-11, "rollout/return_std": 4918186.0, "rollout/ep_rew_mean": -19901605.571878, "rollout/ep_len_mean": 1000.0, "time/fps": 3914, "time/time_elapsed": 206, "time/total_timesteps": 810000}
{"rollout/ep_rew_mean": -19899344.102059335, "rollout/ep_len_mean": 1000.0, "time/fps": 3914, "time/time_elapsed": 209, "time/total_timesteps": 820000}
{"rollout/ep_rew_mean": -19846388.246196836, "rollout/ep_len_mean": 1000.0, "time/fps": 3915, "time/time_elapsed": 211, "time/total_timesteps": 830000}
{"rollout/ep_rew_mean": -19841734.334540375, "rollout/ep_len_mean": 1000.0, "time/fps": 3915, "time/time_elapsed": 214, "time/total_timesteps": 840000}
{"rollout/ep_rew_mean": -19874989.620053273, "rollout/ep_len_mean": 1000.0, "time/fps": 3915, "time/time_elapsed": 217, "time/total_timesteps": 850000}
{"rollout/ep_rew_mean": -18476722.79431407, "rollout/ep_len_mean": 929.0, "time/fps": 3915, "time/time_elapsed": 219, "time/total_timesteps": 860000}
{"train/iterations": 14, "train/delta_std": 0.05, "train/learning_rate": 0.0018, "train/step_size": 4.5522460800917486e-11, "rollout/return_std": 4942615.0, "rollout/ep_rew_mean": -19936765.449364, "rollout/ep_len_mean": 1000.0, "time/fps": 3915, "time/time_elapsed": 222, "time/total_timesteps": 870000}
{"rollout/ep_rew_mean": -14941051.4923565, "rollout/ep_len_mean": 752.75, "time/fps": 3915, "time/time_elapsed": 224, "time/total_timesteps": 880000}
{"rollout/ep_rew_mean": -16989910.785574857, "rollout/ep_len_mean": 858.7142857142857, "time/fps": 3915, "time/time_elapsed": 227, "time/total_timesteps": 890000}
{"rollout/ep_rew_mean": -17656078.072059225, "rollout/ep_len_mean": 890.1111111111111, "time/fps": 3915, "time/time_elapsed": 229, "time/total_timesteps": 900000}
{"rollout/ep_rew_mean": -18207186.329575002, "rollout/ep_len_mean": 917.5833333333334, "time/fps": 3915, "time/time_elapsed": 232, "time/total_timesteps": 910000}
{"rollout/ep_rew_mean": -18426051.9229955, "rollout/ep_len_mean": 929.3571428571429, "time/fps": 3915, "time/time_elapsed": 234, "time/total_timesteps": 920000}
{"train/iterations": 15, "train/delta_std": 0.05, "train/learning_rate": 0.0018, "train/step_size": 4.557393004644972e-11, "rollout/return_std": 4937033.0, "rollout/ep_rew_mean": -10057205.698804, "rollout/ep_len_mean": 509.0, "time/fps": 3915, "time/time_elapsed": 237, "time/total_timesteps": 930000}
{"rollout/ep_rew_mean": -9917545.047021, "rollout/ep_len_mean": 506.1666666666667, "time/fps": 3917, "time/time_elapsed": 239, "time/total_timesteps": 940000}
{"rollout/ep_rew_mean": -13175368.298976336, "rollout/ep_len_mean": 670.7777777777778, "time/fps": 3918, "time/time_elapsed": 242, "time/total_timesteps": 950000}
{"rollout/ep_rew_mean": -13223522.778757667, "rollout/ep_len_mean": 670.6666666666666, "time/fps": 3918, "time/time_elapsed": 244, "time/total_timesteps": 960000}
{"train/iterations": 16, "train/delta_std": 0.05, "train/learning_rate": 0.0018, "train/step_size": 2.3869238183205077e-11, "rollout/return_std": 9426359.0, "time/fps": 3918, "time/time_elapsed": 247, "time/total_timesteps": 970000}
{"rollout/ep_rew_mean": -19899486.773772, "rollout/ep_len_mean": 1000.0, "time/fps": 3918, "time/time_elapsed": 250, "time/total_timesteps": 980000}
{"rollout/ep_rew_mean": -15932675.004548404, "rollout/ep_len_mean": 802.6, "time/fps": 3918, "time/time_elapsed": 252, "time/total_timesteps": 990000}
{"rollout/ep_rew_mean": -15416037.316212334, "rollout/ep_len_mean": 780.0, "time/fps": 3918, "time/time_elapsed": 255, "time/total_timesteps": 1000000}
{"rollout/ep_rew_mean": -14897923.7722065, "rollout/ep_len_mean": 753.0833333333334, "time/fps": 3918, "time/time_elapsed": 257, "time/total_timesteps": 1010000}
{"rollout/ep_rew_mean": -15902100.578067465, "rollout/ep_len_mean": 802.4666666666667, "time/fps": 3918, "time/time_elapsed": 260, "time/total_timesteps": 1020000}
